<?xml version="1.0" encoding="utf-8"?>
<odoo>

    <!-- Add carrier_id field-->
    <record id="carrier_id" model="ir.ui.view">
        <field name="name">carrier_id</field>
        <field name="model">stock.picking.batch</field>
        <field name="inherit_id" ref="stock_picking_batch.stock_picking_batch_form"/>
        <field name="arch" type="xml">
            <xpath expr="//field[@name='user_id']" position="after">
                <field name="carrier_id"/>
            </xpath>
        </field>
    </record>

    <!-- Add domain carrier_id on picking_ids tree  -->
    <record id="filter_carrier_id" model="ir.actions.act_window">
        <field name="name">filter_carrier_id</field>
        <field name="res_model">stock.picking.batch</field>
        <field name="view_mode">tree</field>
        <field name="domain">[('carrier_id', '=', carrier_id)]</field>
    </record>

    <!-- Delivert Request Form -->
    <record id="print_delivery_request_form" model="ir.actions.report">
        <field name="name">Delivery Request Form</field>
        <field name="model">stock.picking.batch</field>
        <field name="report_name">stock.picking.batch</field>
        <field name="report_type">py3o</field>
        <field name="py3o_filetype">pdf</field>
        <field name="module">stock_delivery_request_report</field>
        <field name="py3o_template_fallback">delivery_request_form.odt</field>
      
        <!-- Add entry in "Print" drop-down list -->
        <field name="binding_type">report</field>
        <field name="binding_model_id" ref="stock_picking_batch.model_stock_picking_batch"/>
    </record>

</odoo>
